chansub.py
chansub-0.0.1.dist-info/METADATA
chansub-0.0.1.dist-info/WHEEL
chansub-0.0.1.dist-info/entry_points.txt
chansub-0.0.1.dist-info/top_level.txt
chansub-0.0.1.dist-info/RECORD
