Metadata-Version: 2.1
Name: chansub
Version: 0.0.1
Summary: Number of channel subscribersNumber of channel subscribers
Home-page: https://github.com/ayaka-wada/chansub
Author: ayaka wada
Author-email: s2022040@stu.musashino-u.ac.jp
License: UNKNOWN
Project-URL: Bug Tracker, https://github.com/ayaka-wada/chansub
Platform: UNKNOWN
Classifier: Programming Language :: Python :: 3
Classifier: License :: OSI Approved :: MIT License
Classifier: Operating System :: OS Independent
Requires-Python: >=3.8
